{
    "name": "ParkingPlace",
    "fields": [
        {
            "fieldName": "numberPlace",
            "fieldType": "Integer"
        }
    ],
    "relationships": [
        {
            "relationshipType": "many-to-one",
            "relationshipName": "floor",
            "otherEntityName": "floor",
            "otherEntityField": "id"
        }
    ],
    "changelogDate": "20200511131853",
    "entityTableName": "parking_place",
    "dto": "mapstruct",
    "pagination": "pagination",
    "service": "serviceImpl",
    "jpaMetamodelFiltering": false,
    "fluentMethods": true,
    "clientRootFolder": "parcheggio",
    "applications": "*",
    "microserviceName": "parcheggio"
}